<?xml version="1.0"?>
<wFaceInputPrintStyle>
  <TitleSize>15</TitleSize>
  <MulPageSpace>0</MulPageSpace>
  <DataSize>8</DataSize>
  <TitleHeight>42</TitleHeight>
  <Title>no</Title>
  <LeftMargin>10</LeftMargin>
  <TopMargin>10</TopMargin>
  <wFaceInputPrintCell>
    <PrintCell>wFaceInputPrintCell</PrintCell>
    <Width>507</Width>
    <MappingName>PJName</MappingName>
    <Alignment>center</Alignment>
    <Top>40</Top>
    <Left>55</Left>
    <Height>15</Height>
    <Label>False</Label>
    <DataSize>18</DataSize>
    <Grid>False</Grid>
  </wFaceInputPrintCell>
  <wFaceInputPrintCell>
    <PrintCell>wFaceInputPrintCell</PrintCell>
    <Width>507</Width>
    <MappingName>存  根  联</MappingName>
    <Alignment>center</Alignment>
    <Top>68</Top>
    <Left>55</Left>
    <Height>15</Height>
    <Label>True</Label>
    <DataSize>18</DataSize>
    <Grid>False</Grid>
  </wFaceInputPrintCell>
  <wFaceInputPrintCell>
    <PrintCell>wFaceInputPrintCell</PrintCell>
    <Width>30</Width>
    <MappingName>No</MappingName>
    <Alignment>center</Alignment>
    <Top>68</Top>
    <Left>463</Left>
    <Height>15</Height>
    <Label>True</Label>
    <DataSize>18</DataSize>
    <Grid>False</Grid>
  </wFaceInputPrintCell>
  <wFaceInputPrintCell>
    <PrintCell>wFaceInputPrintCell</PrintCell>
    <Width>150</Width>
    <MappingName>OrderNumber</MappingName>
    <Alignment>left</Alignment>
    <Top>68</Top>
    <Left>486</Left>
    <Height>15</Height>
    <Label>False</Label>
    <DataSize>12</DataSize>
    <Grid>False</Grid>
  </wFaceInputPrintCell>
  <wFaceInputPrintCell>
    <PrintCell>wFaceInputPrintCell</PrintCell>
    <Width>52</Width>
    <MappingName>开票日期：</MappingName>
    <Alignment>left</Alignment>
    <Top>106</Top>
    <Left>60</Left>
    <Height>13</Height>
    <Label>True</Label>
    <DataSize>12</DataSize>
    <Grid>False</Grid>
  </wFaceInputPrintCell>
  <wFaceInputPrintCell>
    <PrintCell>wFaceInputPrintCell</PrintCell>
    <Width>52</Width>
    <MappingName>联系地址：</MappingName>
    <Alignment>left</Alignment>
    <Top>117</Top>
    <Left>60</Left>
    <Height>13</Height>
    <Label>True</Label>
    <DataSize>12</DataSize>
    <Grid>False</Grid>
  </wFaceInputPrintCell>
  <wFaceInputPrintCell>
    <PrintCell>wFaceInputPrintCell</PrintCell>
    <Width>221</Width>
    <MappingName>CreateDate</MappingName>
    <Alignment>left</Alignment>
    <Top>106</Top>
    <Left>112</Left>
    <Height>13</Height>
    <Label>False</Label>
    <DataSize>12</DataSize>
    <Grid>False</Grid>
  </wFaceInputPrintCell>
  <wFaceInputPrintCell>
    <PrintCell>wFaceInputPrintCell</PrintCell>
    <Width>221</Width>
    <MappingName>DlvAdd</MappingName>
    <Alignment>left</Alignment>
    <Top>117</Top>
    <Left>112</Left>
    <Height>13</Height>
    <Label>False</Label>
    <DataSize>12</DataSize>
    <Grid>False</Grid>
  </wFaceInputPrintCell>
  <wFaceInputPrintCell>
    <PrintCell>wFaceInputPrintCell</PrintCell>
    <Width>52</Width>
    <MappingName>购货单位：</MappingName>
    <Alignment>left</Alignment>
    <Top>106</Top>
    <Left>340</Left>
    <Height>13</Height>
    <Label>True</Label>
    <DataSize>12</DataSize>
    <Grid>False</Grid>
  </wFaceInputPrintCell>
  <wFaceInputPrintCell>
    <PrintCell>wFaceInputPrintCell</PrintCell>
    <Width>52</Width>
    <MappingName>电    话：</MappingName>
    <Alignment>left</Alignment>
    <Top>117</Top>
    <Left>340</Left>
    <Height>13</Height>
    <Label>True</Label>
    <DataSize>12</DataSize>
    <Grid>False</Grid>
  </wFaceInputPrintCell>
  <wFaceInputPrintCell>
    <PrintCell>wFaceInputPrintCell</PrintCell>
    <Width>170</Width>
    <MappingName>ChineseName</MappingName>
    <Alignment>left</Alignment>
    <Top>106</Top>
    <Left>390</Left>
    <Height>13</Height>
    <Label>False</Label>
    <DataSize>12</DataSize>
    <Grid>False</Grid>
  </wFaceInputPrintCell>
  <wFaceInputPrintCell>
    <PrintCell>wFaceInputPrintCell</PrintCell>
    <Width>170</Width>
    <MappingName>CustomerPhone</MappingName>
    <Alignment>left</Alignment>
    <Top>117</Top>
    <Left>390</Left>
    <Height>13</Height>
    <Label>False</Label>
    <DataSize>12</DataSize>
    <Grid>False</Grid>
  </wFaceInputPrintCell>
  <wFaceInputPrintCell>
    <PrintCell>wFaceInputPrintCell</PrintCell>
    <Width>52</Width>
    <MappingName>开票人：</MappingName>
    <Alignment>left</Alignment>
    <Top>221</Top>
    <Left>60</Left>
    <Height>13</Height>
    <Label>True</Label>
    <DataSize>12</DataSize>
    <Grid>False</Grid>
  </wFaceInputPrintCell>
  <wFaceInputPrintCell>
    <PrintCell>wFaceInputPrintCell</PrintCell>
    <Width>100</Width>
    <MappingName>OperName</MappingName>
    <Alignment>left</Alignment>
    <Top>221</Top>
    <Left>112</Left>
    <Height>13</Height>
    <Label>False</Label>
    <DataSize>12</DataSize>
    <Grid>False</Grid>
  </wFaceInputPrintCell>
  <wFaceInputPrintCell>
    <PrintCell>wFaceInputPrintCell</PrintCell>
    <Width>52</Width>
    <MappingName>收款人：</MappingName>
    <Alignment>left</Alignment>
    <Top>221</Top>
    <Left>215</Left>
    <Height>13</Height>
    <Label>True</Label>
    <DataSize>12</DataSize>
    <Grid>False</Grid>
  </wFaceInputPrintCell>
  <wFaceInputPrintCell>
    <PrintCell>wFaceInputPrintCell</PrintCell>
    <Width>100</Width>
    <MappingName>MoneyName</MappingName>
    <Alignment>left</Alignment>
    <Top>221</Top>
    <Left>260</Left>
    <Height>13</Height>
    <Label>False</Label>
    <DataSize>12</DataSize>
    <Grid>False</Grid>
  </wFaceInputPrintCell>
  <wFaceInputPrintCell>
    <PrintCell>wFaceInputPrintCell</PrintCell>
    <Width>100</Width>
    <MappingName>开票单位(盖章有效)：</MappingName>
    <Alignment>left</Alignment>
    <Top>221</Top>
    <Left>360</Left>
    <Height>13</Height>
    <Label>True</Label>
    <DataSize>12</DataSize>
    <Grid>False</Grid>
  </wFaceInputPrintCell>
  <wFaceInputPrintCell>
    <PrintCell>wFaceInputPrintCell</PrintCell>
    <Width>507</Width>
    <MappingName>http://172.18.2.122/printtest/xml/SaleGrid.xml</MappingName>
    <Alignment>left</Alignment>
    <Top>130</Top>
    <Left>55</Left>
    <Height>86</Height>
    <Label>False</Label>
    <DataSize>12</DataSize>
    <Grid>True</Grid>
  </wFaceInputPrintCell>
</wFaceInputPrintStyle>